LICENSE.txt
MANIFEST.in
README.md
README.rst
setup.py
f2py_test_package/__init__.py
f2py_test_package/__version__.py
f2py_test_package/cl_utils.py
f2py_test_package/default_settings.yaml
f2py_test_package/setup.cfg
f2py_test_package/utKit.py
f2py_test_package.egg-info/PKG-INFO
f2py_test_package.egg-info/SOURCES.txt
f2py_test_package.egg-info/dependency_links.txt
f2py_test_package.egg-info/not-zip-safe
f2py_test_package.egg-info/requires.txt
f2py_test_package.egg-info/top_level.txt
f2py_test_package/commonutils/__init__.py
f2py_test_package/commonutils/getpackagepath.py
f2py_test_package/tests/__init__.py