Metadata-Version: 1.1
Name: f2py-test-package
Version: 0.1
Summary: A python package and command-line tools to The product of teaching myself to create fortran extenions for python
Home-page: https://github.com/thespacedoctor/f2py_test_package
Author: David Young
Author-email: davidrobertyoung@gmail.com
License: MIT
Download-URL: https://github.com/thespacedoctor/f2py_test_package/archive/v0.1.zip
Keywords: fortran, f2py
Platform: UNKNOWN
Classifier: Development Status :: 4 - Beta
Classifier: License :: OSI Approved :: MIT License
Classifier: Programming Language :: Python :: 2.7
Classifier: Topic :: Utilities
